t8386/__init__.py
t8386/base_account.py
t8386/base_processor.py
t8386/base_rest.py
t8386/base_rest_config.py
t8386/base_wallet.py
t8386/logger.py
t8386/social.py
t8386/supbase_db.py
t8386/task_manager.py
t8386/urban_proxy.py
t8386/utils.py
t8386/wallets.py
t8386-0.1.71.dist-info/licenses/LICENSE
t8386-0.1.71.dist-info/METADATA
t8386-0.1.71.dist-info/WHEEL
t8386-0.1.71.dist-info/top_level.txt
t8386-0.1.71.dist-info/RECORD
