Metadata-Version: 2.4
Name: t8386
Version: 0.1.71
Summary: A Python package for managing blockchain accounts and interactions with REST APIs.
Home-page: https://github.com/tyluudinh/t8386
Author: t8386
Author-email: t8386 <dinhty.luu@gmail.com>
License: MIT
Project-URL: Homepage, https://github.com/tyluudinh/t8386
Project-URL: Bug Tracker, https://github.com/tyluudinh/t8386/issues
Classifier: Development Status :: 3 - Alpha
Classifier: Intended Audience :: Developers
Classifier: License :: OSI Approved :: MIT License
Classifier: Operating System :: OS Independent
Classifier: Programming Language :: Python :: 3
Classifier: Topic :: Software Development :: Libraries :: Python Modules
Classifier: Topic :: System :: Logging
Requires-Python: >=3.7
License-File: LICENSE
Requires-Dist: colorama>=0.4.4
Dynamic: author
Dynamic: home-page
Dynamic: license-file
Dynamic: requires-python
